cninfo/__init__.py
cninfo/hq.py
cninfo/hq_info.py
cninfo/stock_structure.py
cninfo-0.1.0.dist-info/DESCRIPTION.rst
cninfo-0.1.0.dist-info/METADATA
cninfo-0.1.0.dist-info/RECORD
cninfo-0.1.0.dist-info/WHEEL
cninfo-0.1.0.dist-info/metadata.json
cninfo-0.1.0.dist-info/top_level.txt
