Metadata-Version: 2.0
Name: cninfo
Version: 0.1.0
Summary: library to fetch stock info from cninfo
Home-page: https://coding.net/u/YaleZheng/p/cninfo
Author: Yale Zheng
Author-email: yale.zheng@icloud.com
License: Apache Software License
Keywords: cninfo stock
Platform: UNKNOWN
Classifier: Development Status :: 3 - Alpha
Classifier: Intended Audience :: Developers
Classifier: License :: OSI Approved :: Apache Software License
Classifier: Programming Language :: Python :: 2
Classifier: Programming Language :: Python :: 3
Requires-Dist: chardet
Requires-Dist: pandas
Requires-Dist: requests
Requires-Dist: requests-cache
Requires-Dist: tabulate
